gdrive_datastore/__init__.py
gdrive_datastore/gdrive.py
gdrive_datastore-0.0.1.5.dist-info/METADATA
gdrive_datastore-0.0.1.5.dist-info/WHEEL
gdrive_datastore-0.0.1.5.dist-info/licenses/LICENSE
gdrive_datastore-0.0.1.5.dist-info/RECORD
