Metadata-Version: 2.1
Name: gdrive-datastore
Version: 0.0.1.5
Summary: A package to facilitate storing data on Google Drive.
Project-URL: Homepage, https://github.com/ChenglimEar/gdrive-datastore
Project-URL: Bug Tracker, https://github.com/ChenglimEar/gdrive-datastore/issues
Author-email: Chenglim Ear <chenglim.ear@gmail.com>
License-File: LICENSE
Classifier: License :: OSI Approved :: MIT License
Classifier: Operating System :: OS Independent
Classifier: Programming Language :: Python :: 3
Requires-Python: >=3.7
Requires-Dist: oauth2client>=4.1.3
Requires-Dist: pydrive2>=1.17.0
